Workbook

Sheet Dashboard
A1: MONSTER BEVERAGE CORPORATION (MNST) · EQUITY RESEARCH & FORECASTING MODEL
A3: FY2022–FY2024 Historical | FY2025E–FY2029E Forecast | DCF Intrinsic Value | Assumptions-Driven
A5: KEY MODEL ASSUMPTIONS SNAPSHOT
A6: Assumption | B6: FY2025E | C6: FY2026E | D6: FY2027E | E6: FY2028E | F6: FY2029E
A7: Monster Energy® Drinks growth % | B7: =Assumptions!E6 -> 0.07 | C7: =Assumptions!F6 -> 0.08 | D7: =Assumptions!G6 -> 0.08 | E7: =Assumptions!H6 -> 0.07 | F7: =Assumptions!I6 -> 0.07
A8: Strategic Brands growth % | B8: =Assumptions!E7 -> 0.15 | C8: =Assumptions!F7 -> 0.12 | D8: =Assumptions!G7 -> 0.1 | E8: =Assumptions!H7 -> 0.08 | F8: =Assumptions!I7 -> 0.08
A9: Gross margin % | B9: =Assumptions!E12 -> 0.545 | C9: =Assumptions!F12 -> 0.55 | D9: =Assumptions!G12 -> 0.555 | E9: =Assumptions!H12 -> 0.558 | F9: =Assumptions!I12 -> 0.56
A10: G&A % of net sales (adj.) | B10: =Assumptions!E15 -> 0.135 | C10: =Assumptions!F15 -> 0.132 | D10: =Assumptions!G15 -> 0.13 | E10: =Assumptions!H15 -> 0.128 | F10: =Assumptions!I15 -> 0.125
A11: D&A ($M) | B11: =Assumptions!E19 -> 125 | C11: =Assumptions!F19 -> 135 | D11: =Assumptions!G19 -> 145 | E11: =Assumptions!H19 -> 155 | F11: =Assumptions!I19 -> 165
A12: CapEx ($M) | B12: =Assumptions!E20 -> 280 | C12: =Assumptions!F20 -> 295 | D12: =Assumptions!G20 -> 310 | E12: =Assumptions!H20 -> 320 | F12: =Assumptions!I20 -> 330
A13: Effective tax rate % | B13: =Assumptions!E27 -> 0.24 | C13: =Assumptions!F27 -> 0.24 | D13: =Assumptions!G27 -> 0.24 | E13: =Assumptions!H27 -> 0.24 | F13: =Assumptions!I27 -> 0.24
A14: Diluted shares (M) | B14: =Assumptions!E36 -> 985 | C14: =Assumptions!F36 -> 963 | D14: =Assumptions!G36 -> 940 | E14: =Assumptions!H36 -> 916 | F14: =Assumptions!I36 -> 893
A15: Share buybacks ($M) | B15: =Assumptions!E35 -> 500 | C15: =Assumptions!F35 -> 600 | D15: =Assumptions!G35 -> 700 | E15: =Assumptions!H35 -> 700 | F15: =Assumptions!I35 -> 700
A16: WACC % | B16: =Assumptions!D40 -> 0.09 | C16: =Assumptions!E40 -> — | D16: =Assumptions!F40 -> — | E16: =Assumptions!G40 -> — | F16: =Assumptions!H40 -> —
A17: Terminal growth rate % | B17: =Assumptions!D41 -> 0.04 | C17: =Assumptions!E41 -> — | D17: =Assumptions!F41 -> — | E17: =Assumptions!G41 -> — | F17: =Assumptions!H41 -> —
A20: INCOME STATEMENT SUMMARY ($thousands)
B21: FY2022A | C21: FY2023A | D21: FY2024A | E21: FY2025E | F21: FY2026E | G21: FY2027E | H21: FY2028E | I21: FY2029E
A22: Net Sales | B22: ='Income Statement'!B10 -> 6311050 | C22: ='Income Statement'!C10 -> 7140027 | D22: ='Income Statement'!D10 -> 7492709 | E22: ='Income Statement'!E10 -> 0 | F22: ='Income Statement'!F10 -> 0 | G22: ='Income Statement'!G10 -> 0 | H22: ='Income Statement'!H10 -> 0 | I22: ='Income Statement'!I10 -> 0
A23: Gross Profit | B23: ='Income Statement'!B15 -> 3174567 | C23: ='Income Statement'!C15 -> 3794206 | D23: ='Income Statement'!D15 -> 4048878 | E23: ='Income Statement'!E15 -> 0 | F23: ='Income Statement'!F15 -> 0 | G23: ='Income Statement'!G15 -> 0 | H23: ='Income Statement'!H15 -> 0 | I23: ='Income Statement'!I15 -> 0
A24: GM % | B24: ='Income Statement'!B16 -> 0.50301725 | C24: ='Income Statement'!C16 -> 0.53139939 | D24: ='Income Statement'!D16 -> 0.54037572 | E24: ='Income Statement'!E16 -> 0 | F24: ='Income Statement'!F16 -> 0 | G24: ='Income Statement'!G16 -> 0 | H24: ='Income Statement'!H16 -> 0 | I24: ='Income Statement'!I16 -> 0
A25: EBITDA | B25: ='Income Statement'!B29 -> 1655217 | C25: ='Income Statement'!C29 -> 2038343 | D25: ='Income Statement'!D29 -> 2044015 | E25: ='Income Statement'!E29 -> 0 | F25: ='Income Statement'!F29 -> 0 | G25: ='Income Statement'!G29 -> 0 | H25: ='Income Statement'!H29 -> 0 | I25: ='Income Statement'!I29 -> 0
A26: EBITDA % | B26: ='Income Statement'!B30 -> 0.26227284 | C26: ='Income Statement'!C30 -> 0.28548113 | D26: ='Income Statement'!D30 -> 0.27280053 | E26: ='Income Statement'!E30 -> 0 | F26: ='Income Statement'!F30 -> 0 | G26: ='Income Statement'!G30 -> 0 | H26: ='Income Statement'!H30 -> 0 | I26: ='Income Statement'!I30 -> 0
A27: EBIT | B27: ='Income Statement'!B26 -> 1585031 | C27: ='Income Statement'!C26 -> 1953836 | D27: ='Income Statement'!D26 -> 1930294 | E27: ='Income Statement'!E26 -> 0 | F27: ='Income Statement'!F26 -> 0 | G27: ='Income Statement'!G26 -> 0 | H27: ='Income Statement'!H26 -> 0 | I27: ='Income Statement'!I26 -> 0
A28: EBIT % | B28: ='Income Statement'!B27 -> 0.25115171 | C28: ='Income Statement'!C27 -> 0.27364546 | D28: ='Income Statement'!D27 -> 0.25762298 | E28: ='Income Statement'!E27 -> 0 | F28: ='Income Statement'!F27 -> 0 | G28: ='Income Statement'!G27 -> 0 | H28: ='Income Statement'!H27 -> 0 | I28: ='Income Statement'!I27 -> 0
A29: Net Income | B29: ='Income Statement'!B42 -> 1190866 | C29: ='Income Statement'!C42 -> 1516086 | D29: ='Income Statement'!D42 -> 1509048 | E29: ='Income Statement'!E42 -> 0 | F29: ='Income Statement'!F42 -> 0 | G29: ='Income Statement'!G42 -> 0 | H29: ='Income Statement'!H42 -> 0 | I29: ='Income Statement'!I42 -> 0
A30: NI Margin % | B30: ='Income Statement'!B43 -> 0.18869538 | C30: ='Income Statement'!C43 -> 0.21233617 | D30: ='Income Statement'!D43 -> 0.20140219 | E30: ='Income Statement'!E43 -> 0 | F30: ='Income Statement'!F43 -> 0 | G30: ='Income Statement'!G43 -> 0 | H30: ='Income Statement'!H43 -> 0 | I30: ='Income Statement'!I43 -> 0
A31: Diluted EPS | B31: ='Income Statement'!B46 -> 1.1170303 | C31: ='Income Statement'!C46 -> 1.4329735 | D31: ='Income Statement'!D46 -> 1.4895351 | E31: ='Income Statement'!E46 -> 0 | F31: ='Income Statement'!F46 -> 0 | G31: ='Income Statement'!G46 -> 0 | H31: ='Income Statement'!H46 -> 0 | I31: ='Income Statement'!I46 -> 0
A32: EPS Growth % | B32: ='Income Statement'!B47 -> 0 | C32: ='Income Statement'!C47 -> 0.28284214 | D32: ='Income Statement'!D47 -> 0.039471458 | E32: ='Income Statement'!E47 -> 0 | F32: ='Income Statement'!F47 -> 0 | G32: ='Income Statement'!G47 -> 0 | H32: ='Income Statement'!H47 -> 0 | I32: ='Income Statement'!I47 -> 0
A35: VALUATION SUMMARY
A36: Method | B36: Implied Price ($) | C36: Upside / (Dn)
A37: DCF (Gordon Growth) | B37: ='DCF Valuation'!B26 -> 0 | C37: =('DCF Valuation'!B26-#REF!)/#REF! -> #REF! | D37: WACC=9.0%, TGR=4.0%
A38: EV/EBITDA (27.0x FY29E) | B38: ='DCF Valuation'!B37 -> 0 | C38: =('DCF Valuation'!B37-#REF!)/#REF! -> #REF! | D38: FY2029E EBITDA × 27x exit
A39: P/E (30.0x FY29E EPS) | B39: ='DCF Valuation'!B42 -> 0 | C39: =('DCF Valuation'!B42-#REF!)/#REF! -> #REF! | D39: FY2029E EPS × 30x exit
A41: Disclaimer: This is a financial model for analytical purposes only, not investment advice. Source: MNST 10-K FY2024 (SEC EDGAR #0001410578-25-000248), Q4 2024 Earnings Release (Feb 27, 2025).
A42: Model structure: Dashboard → Assumptions (edit here) → Income Statement → Balance Sheet → Cash Flow → DCF Valuation

Sheet Master sheet
A1: MONSTER BEVERAGE CORPORATION (MNST) — FORECASTING MODEL ASSUMPTIONS
A2: Blue cells = hardcoded inputs (change these to update the entire model) | All $ amounts in millions unless noted
A4: ASSUMPTION | B4: FY2022 Actual | C4: FY2023 Actual | D4: FY2024 Actual | E4: FY2025E | F4: FY2026E | G4: FY2027E | H4: FY2028E | I4: FY2029E
A5: REVENUE GROWTH ASSUMPTIONS
A6: Monster Energy® Drinks — net sales growth % | B6: 0.257 | C6: 0.129 | D6: 0.049 | E6: 0.117 | F6: 0.112 | G6: 0.107 | H6: 0.102 | I6: 0.105
A7: Strategic Brands — net sales growth % | B7: -0.099 | C7: -0.018 | D7: 0.148 | E7: 0.084 | F7: 0.08 | G7: 0.08 | H7: 0.08 | I7: 0.08
A8: Alcohol Brands — net sales growth % | B8: N/A | C8: 0.823 | D8: -0.068 | E8: -0.218 | F8: -0.2 | G8: -0.2 | H8: -0.2 | I8: -0.2
A9: Other (AFF third-party) — net sales growth % | B9: N/A | C9: 0.237 | D9: 0.002 | E9: 0.03 | F9: 0.03 | G9: 0.03 | H9: 0.03 | I9: 0.03
A11: GROSS MARGIN & OPERATING EXPENSE ASSUMPTIONS
A12: Gross margin % | B12: 0.503 | C12: 0.531 | D12: 0.54 | E12: 0.545 | F12: 0.55 | G12: 0.555 | H12: 0.558 | I12: 0.56
A13: Distribution expense % of net sales | B13: 0.036 | C13: 0.038 | D13: 0.039 | E13: 0.039 | F13: 0.038 | G13: 0.038 | H13: 0.037 | I13: 0.037
A14: Selling expense % of net sales | B14: 0.076 | C14: 0.084 | D14: 0.09 | E14: 0.091 | F14: 0.092 | G14: 0.09 | H14: 0.09 | I14: 0.09
A15: G&A expense % of net sales (adj., ex-impair) | B15: 0.118 | C15: 0.13 | D15: 0.154 | E15: 0.135 | F15: 0.132 | G15: 0.13 | H15: 0.128 | I15: 0.125
A16: Non-recurring / impairment charges ($M) | B16: 138.2 | C16: 42.7 | D16: 138.8 | E16: 0 | F16: 0 | G16: 0 | H16: 0 | I16: 0
A18: D&A, CAPEX & STOCK-BASED COMPENSATION ($M)
A19: Depreciation & amortization % of PPE | B19: =B82/B116 -> 0.140372 | C19: =C82/C116 -> 0.094866838 | D19: =D82/D116 -> 0.10861356 | E19: 0.1 | F19: 0.1 | G19: 0.1 | H19: 0.1 | I19: 0.1
A20: Capital expenditures ($M) | B20: 127 | C20: 221.3 | D20: 264.1 | E20: 280 | F20: 295 | G20: 310 | H20: 320 | I20: 330
A21: Stock-based compensation % of G&A expense | B21: =B146/B75 -> 0.082920243 | C21: =C146/C75 -> 0.073352688 | D21: =D146/D75 -> 0.081208805 | E21: 0.08 | F21: 0.08 | G21: 0.08 | H21: 0.08 | I21: 0.08
A23: BELOW-THE-LINE ASSUMPTIONS
A24: Interest income ($M) | B24: 7.2 | C24: 130 | D24: 115 | E24: 75 | F24: 80 | G24: 85 | H24: 90 | I24: 95
A25: Interest expense ($M) | B25: 1.3 | C25: 0.4 | D25: 27.9 | E25: 48 | F25: 46 | G25: 44 | H25: 25 | I25: 25
A26: FX & other income/(expense) ($M) | B26: -19.8 | C26: -129.9 | D26: -27.9 | E26: -30 | F26: -30 | G26: -30 | H26: -30 | I26: -30
A27: Effective tax rate % | B27: 0.242 | C27: 0.211 | D27: 0.241 | E27: 0.24 | F27: 0.24 | G27: 0.24 | H27: 0.24 | I27: 0.24
A29: WORKING CAPITAL ASSUMPTIONS (DAYS)
A30: Days Sales Outstanding (DSO) | B30: 61.7 | C30: 61 | D30: 59.5 | E30: 58 | F30: 57 | G30: 57 | H30: 56 | I30: 56
A31: Days Inventory Outstanding (DIO) | B31: 97.2 | C31: 106 | D31: 78.1 | E31: 82 | F31: 78 | G31: 75 | H31: 73 | I31: 72
A32: Days Payable Outstanding (DPO) | B32: 54.7 | C32: 61.5 | D32: 49.5 | E32: 52 | F32: 52 | G32: 52 | H32: 52 | I32: 52
A33: Accured Liabilities and other current in % of net sales | B33: =B124/B64 -> 0.098240388 | C33: =C124/C64 -> 0.082813412 | D33: =D124/D64 -> 0.083405615 | E33: 0.085 | F33: 0.085 | G33: 0.085 | H33: 0.085 | I33: 0.085
A34: Short Term Investments ($M) | B34: =B109/1000 -> 516 | C34: =C109/1000 -> 955.605 | D34: =D109/1000 -> 0 | E34: 500 | F34: 500 | G34: 500 | H34: 500 | I34: 500
A35: Goodwill | B35: =B117 -> 1375000 | C35: =C117 -> 1417941 | D35: =D117 -> 1331643 | E35: 1350000 | F35: 1350000 | G35: 1350000 | H35: 1350000 | I35: 1350000
A36: % change of Prepaid Expenses | B36: - | C36: =(C112-B112)/B112 -> -0.17707246 | D36: =(D112-C112)/C112 -> -0.1225858 | E36: -0.1 | F36: -0.1 | G36: -0.1 | H36: -0.1 | I36: -0.1
A37: CAPITAL STRUCTURE & BUYBACK ASSUMPTIONS
A38: Share repurchases ($M) | B38: 193 | C38: 573.8 | D38: 762.1 | E38: 500 | F38: 600 | G38: 700 | H38: 700 | I38: 700
A39: Diluted shares outstanding (M, period avg) | B39: 1066.1 | C39: 1058 | D39: 1013.1 | E39: 985 | F39: 963 | G39: 940 | H39: 916 | I39: 893
A40: Long-term debt outstanding ($M, period end) | B40: 0 | C40: 0 | D40: 374 | E40: 374 | F40: 324 | G40: 274 | H40: 224 | I40: 174
A41: VALUATION & DCF INPUTS
A42: WACC % | B42: — | C42: — | D42: 0.07 | E42: — | F42: — | G42: — | H42: — | I42: —
A43: Terminal growth rate % | B43: — | C43: — | D43: 0.05 | E43: — | F43: — | G43: — | H43: — | I43: —
A44: EV/EBITDA exit multiple (FY2029E) | B44: — | C44: — | D44: 20 | E44: — | F44: — | G44: — | H44: — | I44: —
A45: P/E exit multiple (FY2029E) | B45: — | C45: — | D45: 25 | E45: — | F45: — | G45: — | H45: — | I45: —
A46: Current share price ($) | B46: — | C46: — | D46: 55 | E46: — | F46: — | G46: — | H46: — | I46: —
A47: Net debt FY2024 actual ($M) | B47: — | C47: — | D47: -1159.3 | E47: — | F47: — | G47: — | H47: — | I47: —
A55: MONSTER BEVERAGE CORPORATION — CONSOLIDATED INCOME STATEMENT
A56: Historical: Blue (hardcoded from 10-K) | Forecast: Black formulas driven by Assumptions sheet | $thousands unless noted
B58: FY2022 | C58: FY2023 | D58: FY2024 | E58: FY2025E | F58: FY2026E | G58: FY2027E | H58: FY2028E | I58: FY2029E
A59: NET SALES BY SEGMENT ($THOUSANDS)
A60: Monster Energy® Drinks | B60: 5804000 | C60: 6550612 | D60: 6860146 | E60: =D60*(1+E6) -> 7662783.1 | F60: =E60*(1+F6) -> 8521014.8 | G60: =F60*(1+G6) -> 9432763.4 | H60: =G60*(1+H6) -> 10394905 | I60: =H60*(1+I6) -> 11486370
A61: Strategic Brands | B61: 383000 | C61: 376558 | D61: 432201 | E61: =D61*(1+E7) -> 468505.88 | F61: =E61*(1+F7) -> 505986.35 | G61: =F61*(1+G7) -> 546465.26 | H61: =G61*(1+H7) -> 590182.48 | I61: =H61*(1+I7) -> 637397.08
A62: Alcohol Brands | B62: 101405 | C62: 184855 | D62: 172313 | E62: =D62*(1+E8) -> 134748.77 | F62: =E62*(1+F8) -> 107799.01 | G62: =F62*(1+G8) -> 86239.21 | H62: =G62*(1+H8) -> 68991.368 | I62: =H62*(1+I8) -> 55193.095
A63: Other | B63: 22645 | C63: 28002 | D63: 28049 | E63: =D63*(1+E9) -> 28890.47 | F63: =E63*(1+F9) -> 29757.184 | G63: =F63*(1+G9) -> 30649.9 | H63: =G63*(1+H9) -> 31569.397 | I63: =H63*(1+I9) -> 32516.479
A64: TOTAL NET SALES | B64: =SUM(B60:B63) -> 6311050 | C64: =SUM(C60:C63) -> 7140027 | D64: =SUM(D60:D63) -> 7492709 | E64: =SUM(E60:E63) -> 8294928.2 | F64: =SUM(F60:F63) -> 9164557.3 | G64: =SUM(G60:G63) -> 10096118 | H64: =SUM(H60:H63) -> 11085648 | I64: =I60+I61+I62+I63 -> 12211477
A65: YoY Growth % | C65: =(C64-B64)/B64 -> 0.13135326 | D65: =(D64-C64)/C64 -> 0.049395051 | E65: =(E64-D64)/D64 -> 0.10706664 | F65: =(F64-E64)/E64 -> 0.10483866 | G65: =(G64-F64)/F64 -> 0.10164816 | H65: =(H64-G64)/G64 -> 0.098011014 | I65: =(I64-H64)/H64 -> 0.10155729
A67: COST OF SALES & GROSS PROFIT
A68: Cost of sales | B68: 3136483 | C68: 3345821 | D68: 3443831 | E68: =E64-E69 -> 3774192.3 | F68: =F64-F69 -> 4124050.8 | G68: =G64-G69 -> 4492772.4 | H68: =H64-H69 -> 4899856.6 | I68: =I64-I69 -> 5373049.9
A69: GROSS PROFIT | B69: =B64-B68 -> 3174567 | C69: =C64-C68 -> 3794206 | D69: =D64-D68 -> 4048878 | E69: =E64*E12 -> 4520735.9 | F69: =F64*F12 -> 5040506.5 | G69: =G64*G12 -> 5603345.3 | H69: =H64*H12 -> 6185791.9 | I69: =I64*I12 -> 6838427.1
A70: Gross margin % | B70: =B69/B64 -> 0.50301725 | C70: =C69/C64 -> 0.53139939 | D70: =D69/D64 -> 0.54037572 | E70: =E69/E64 -> 0.545 | F70: =F69/F64 -> 0.55 | G70: =G69/G64 -> 0.555 | H70: =H69/H64 -> 0.558 | I70: =I69/I64 -> 0.56
A72: OPERATING EXPENSES
A73: Distribution expenses | B73: 226491 | C73: 271118 | D73: 289618 | E73: =E64*E13 -> 323502.2 | F73: =F64*F13 -> 348253.18 | G73: =G64*G13 -> 383652.47 | H73: =H64*H13 -> 410168.99 | I73: =I64*I13 -> 451824.65
A74: Selling expenses | B74: 479046 | C74: 596516 | D74: 677038 | E74: =E64*E14 -> 754838.47 | F74: =F64*F14 -> 843139.28 | G74: =G64*G14 -> 908650.6 | H74: =H64*H14 -> 997708.36 | I74: =I64*I14 -> 1099032.9
A75: General & administrative (adj.) | B75: 745801 | C75: 930000 | D75: 1013166 | E75: =E64*E15 -> 1119815.3 | F75: =F64*F15 -> 1209721.6 | G75: =G64*G15 -> 1312495.3 | H75: =H64*H15 -> 1418963 | I75: =I64*I15 -> 1526434.6
A76: Non-recurring / impairment charges | B76: 138198 | C76: 42736 | D76: 138762 | E76: =E16 -> 0 | F76: =F16 -> 0 | G76: =G16 -> 0 | H76: =H16 -> 0 | I76: =I16 -> 0
A77: TOTAL OPERATING EXPENSES | B77: =B73+B74+B75+B76 -> 1589536 | C77: =C73+C74+C75+C76 -> 1840370 | D77: =D73+D74+D75+D76 -> 2118584 | E77: =SUM(E73:E76) -> 2198156 | F77: =SUM(F73:F76) -> 2401114 | G77: =SUM(G73:G76) -> 2604798.4 | H77: =SUM(H73:H76) -> 2826840.4 | I77: =SUM(I73:I76) -> 3077292.2
A78: Total opex % of net sales (adj. excl impairment) | B78: =(B73+B74+B75)/B64 -> 0.22996775 | C78: =(C73+C74+C75)/C64 -> 0.25176852 | D78: =(D73+D74+D75)/D64 -> 0.26423314 | E78: =E77/E64 -> 0.265 | F78: =F77/F64 -> 0.262 | G78: =G77/G64 -> 0.258 | H78: =H77/H64 -> 0.255 | I78: =I77/I64 -> 0.252
A80: OPERATING INCOME (EBIT) | B80: =B69-B77 -> 1585031 | C80: =C69-C77 -> 1953836 | D80: =D69-D77 -> 1930294 | E80: =E69-E77 -> 2322579.9 | F80: =F69-F77 -> 2639392.5 | G80: =G69-G77 -> 2998547 | H80: =H69-H77 -> 3358951.5 | I80: =I69-I77 -> 3761134.9
A81: EBIT margin % | B81: =B80/B64 -> 0.25115171 | C81: =C80/C64 -> 0.27364546 | D81: =D80/D64 -> 0.25762298 | E81: =E70-E78 -> 0.28 | F81: =F70-F78 -> 0.288 | G81: =G70-G78 -> 0.297 | H81: =H70-H78 -> 0.303 | I81: =I70-I78 -> 0.308
A82: Add: Depreciation & amortization ($K) | B82: 70186 | C82: 84507 | D82: 113721 | E82: =E116*E19 -> 94260.16 | F82: =F116*F19 -> 84863.644 | G82: =G116*G19 -> 76408.28 | H82: =H116*H19 -> 68799.452 | I82: =I116*I19 -> 61952.506
A83: EBITDA | B83: =B80+B82 -> 1655217 | C83: =C80+C82 -> 2038343 | D83: =D80+D82 -> 2044015 | E83: =E80+E82 -> 2416840.1 | F83: =F80+F82 -> 2724256.2 | G83: =G80+G82 -> 3074955.2 | H83: =H80+H82 -> 3427750.9 | I83: =I80+I82 -> 3823087.4
A84: EBITDA margin % | B84: =B83/B64 -> 0.26227284 | C84: =C83/C64 -> 0.28548113 | D84: =D83/D64 -> 0.27280053 | E84: =E83/E64 -> 0.29136359 | F84: =F83/F64 -> 0.29725998 | G84: =G83/G64 -> 0.30456809 | H84: =H83/H64 -> 0.30920617 | I84: =I83/I64 -> 0.3130733
A86: NON-OPERATING INCOME / (EXPENSE)
A87: Interest income | B87: 7226 | C87: 130014 | D87: 115022 | E87: =E24*1000 -> 75000 | F87: =F24*1000 -> 80000 | G87: =G24*1000 -> 85000 | H87: =H24*1000 -> 90000 | I87: =I24*1000 -> 95000
A88: Interest expense | B88: -1289 | C88: -383 | D88: -27916 | E88: =E25*-1000 -> -48000 | F88: =F25*-1000 -> -46000 | G88: =G25*-1000 -> -44000 | H88: =H25*-1000 -> -25000 | I88: =I25*-1000 -> -25000
A89: FX & other income/(expense) | B89: -19762 | C89: -129887 | D89: -27941 | E89: =E26*1000 -> -30000 | F89: =F26*1000 -> -30000 | G89: =G26*1000 -> -30000 | H89: =H26*1000 -> -30000 | I89: =I26*1000 -> -30000
A90: Total other income/(expense), net | B90: =B87+B88+B89 -> -13825 | C90: =C87+C88+C89 -> -256 | D90: =D87+D88+D89 -> 59165 | E90: =E87+E88+E91 -> 27000 | F90: =F87+F88+F91 -> 34000 | G90: =G87+G88+G91 -> 41000 | H90: =H87+H88+H91 -> 65000 | I90: =I87+I88+I91 -> 70000
A92: INCOME BEFORE PROVISION FOR INCOME TAXES | B92: =B80+B90 -> 1571206 | C92: =C80+C90 -> 1953580 | D92: =D80+D90 -> 1989459 | E92: =E80+E90 -> 2349579.9 | F92: =F80+F90 -> 2673392.5 | G92: =G80+G90 -> 3039547 | H92: =H80+H90 -> 3423951.5 | I92: =I80+I90 -> 3831134.9
A93: Provision for income taxes | B93: 380340 | C93: 437494 | D93: 480411 | E93: =E92*E94 -> 563899.18 | F93: =F92*F94 -> 641614.2 | G93: =G92*G94 -> 729491.27 | H93: =H92*H94 -> 821748.36 | I93: =I92*I94 -> 919472.38
A94: Effective tax rate % | B94: =IF(B92>0,B93/B92,0) -> 0.24206883 | C94: =IF(C92>0,C93/C92,0) -> 0.22394476 | D94: =IF(D92>0,D93/D92,0) -> 0.24147821 | E94: =E27 -> 0.24 | F94: =F27 -> 0.24 | G94: =G27 -> 0.24 | H94: =H27 -> 0.24 | I94: =I27 -> 0.24
A96: NET INCOME | B96: =B92-B93 -> 1190866 | C96: =C92-C93 -> 1516086 | D96: =D92-D93 -> 1509048 | E96: =E92-E93 -> 1785680.7 | F96: =F92-F93 -> 2031778.3 | G96: =G92-G93 -> 2310055.7 | H96: =H92-H93 -> 2602203.1 | I96: =I92-I93 -> 2911662.5
A97: Net income margin % | B97: =B96/B64 -> 0.18869538 | C97: =C96/C64 -> 0.21233617 | D97: =D96/D64 -> 0.20140219 | E97: =E96/E64 -> 0.2152738 | F97: =F96/F64 -> 0.22169956 | G97: =G96/G64 -> 0.22880633 | H97: =H96/H64 -> 0.23473621 | I97: =I96/I64 -> 0.23843656
A99: Diluted shares outstanding (millions) | B99: 1066.1 | C99: 1058 | D99: 1013.1 | E99: 1025 | F99: 1025 | G99: 1025 | H99: 1025 | I99: 1025
A100: DILUTED EPS ($) | B100: =B96/B99/1000 -> 1.1170303 | C100: =C96/C99/1000 -> 1.4329735 | D100: =D96/D99/1000 -> 1.4895351 | E100: =E96/E99/1000 -> 1.7421275 | F100: =F96/F99/1000 -> 1.9822227 | G100: =G96/G99/1000 -> 2.2537129 | H100: =H96/H99/1000 -> 2.5387348 | I100: =I96/I99/1000 -> 2.8406464
A101: YoY EPS growth % | C101: =IF(B100<>0,(C100-B100)/B100,"") -> 0.28284214 | D101: =IF(C100<>0,(D100-C100)/C100,"") -> 0.039471458 | E101: =IF(D100<>0,(E100-D100)/D100,"") -> 0.16957804 | F101: =IF(E100<>0,(F100-E100)/E100,"") -> 0.13781724 | G101: =IF(F100<>0,(G100-F100)/F100,"") -> 0.13696248 | H101: =IF(G100<>0,(H100-G100)/G100,"") -> 0.1264677 | I101: =IF(H100<>0,(I100-H100)/H100,"") -> 0.11892207
A103: MONSTER BEVERAGE CORPORATION — CONSOLIDATED BALANCE SHEET
A104: Historical: Blue (hardcoded from 10-K) | Forecast: formulas driven by IS + Assumptions | $thousands
B106: FY2022 | C106: FY2023 | D106: FY2024 | E106: FY2025E | F106: FY2026E | G106: FY2027E | H106: FY2028E | I106: FY2029E
A107: CURRENT ASSETS
A108: Cash and cash equivalents | B108: 1460000 | C108: 2297675 | D108: 1533287
A109: Short-term investments | B109: 516000 | C109: 955605 | D109: 0 | E109: =E34*1000 -> 500000 | F109: =F34*1000 -> 500000 | G109: =G34*1000 -> 500000 | H109: =H34*1000 -> 500000 | I109: =I34*1000 -> 500000
A110: Accounts receivable, net | B110: 1067000 | C110: 1193964 | D110: 1221646 | E110: =E64*E30/365 -> 1318098.2 | F110: =F64*F30/365 -> 1431177.4 | G110: =G64*G30/365 -> 1576654 | H110: =H64*H30/365 -> 1700811.8 | I110: =I64*I30/365 -> 1873541.7
A111: Inventories | B111: 835000 | C111: 971406 | D111: 737107 | E111: =E68*E31/365 -> 847900.74 | F111: =F68*F31/365 -> 881304.01 | G111: =G68*G31/365 -> 923172.41 | H111: =H68*H31/365 -> 979971.33 | I111: =I68*I31/365 -> 1059889.3
A112: Prepaid expenses & other current assets | B112: 207000 | C112: 170346 | D112: 149464 | E112: =D112*(1+E36) -> 134517.6 | F112: =E112*(1+F36) -> 121065.84 | G112: =F112*(1+G36) -> 108959.26 | H112: =G112*(1+H36) -> 98063.33 | I112: =H112*(1+I36) -> 88256.997
A113: TOTAL CURRENT ASSETS | B113: =B108+B109+B110+B111+B112 -> 4085000 | C113: =C108+C109+C110+C111+C112 -> 5588996 | D113: =D108+D109+D110+D111+D112 -> 3641504
A115: NON-CURRENT ASSETS
A116: Property and equipment, net | B116: 500000 | C116: 890796 | D116: 1047024 | E116: =D116*(1-E19)+E20 -> 942601.6 | F116: =E116*(1-F19)+F20 -> 848636.44 | G116: =F116*(1-G19)+G20 -> 764082.8 | H116: =G116*(1-H19)+H20 -> 687994.52 | I116: =H116*(1-I19)+I20 -> 619525.06
A117: Goodwill | B117: 1375000 | C117: 1417941 | D117: 1331643 | E117: =E35 -> 1350000 | F117: =F35 -> 1350000 | G117: =G35 -> 1350000 | H117: =H35 -> 1350000 | I117: =I35 -> 1350000
A118: Other intangible assets, net | B118: 310000 | C118: 1427139 | D118: 1414252 | E118: 1400000 | F118: 1400000 | G118: 1400000 | H118: 1400000 | I118: 1400000
A119: Deferred income taxes & other non-current | B119: 320000 | C119: 285219 | D119: 284666 | E119: 300000 | F119: 300000 | G119: 300000 | H119: 300000 | I119: 300000
A120: TOTAL ASSETS | B120: =B113+B116+B117+B118+B119 -> 6590000 | C120: =C113+C116+C117+C118+C119 -> 9610091 | D120: =D113+D116+D117+D118+D119 -> 7719089
A122: CURRENT LIABILITIES
A123: Accounts payable | B123: 470000 | C123: 564379 | D123: 466775 | E123: =E68*E32/365 -> 537693.15 | F123: =F68*F32/365 -> 587536 | G123: =G68*G32/365 -> 640066.2 | H123: =H68*H32/365 -> 698061.77 | I123: =I68*I32/365 -> 765475.6
A124: Accrued liabilities & other current | B124: 620000 | C124: 591290 | D124: 624934 | E124: =E64*E33 -> 705068.9 | F124: =F64*F33 -> 778987.37 | G124: =G64*G33 -> 858170.01 | H124: =H64*H33 -> 942280.12 | I124: =I64*I33 -> 1037975.5
...

Sheet Assumptions
A1: MONSTER BEVERAGE CORPORATION (MNST) — FORECASTING MODEL ASSUMPTIONS
A2: Blue cells = hardcoded inputs (change these to update the entire model) | All $ amounts in millions unless noted
A4: ASSUMPTION | B4: FY2022 Actual | C4: FY2023 Actual | D4: FY2024 Actual | E4: FY2025E | F4: FY2026E | G4: FY2027E | H4: FY2028E | I4: FY2029E | J4: RATIONALE / BASIS
A5: REVENUE GROWTH ASSUMPTIONS
A6: Monster Energy® Drinks — net sales growth % | B6: 0.257 | C6: 0.129 | D6: 0.049 | E6: 0.07 | F6: 0.08 | G6: 0.08 | H6: 0.07 | I6: 0.07 | J6: FY25: ~7% driven by intl expansion & Nov-24 price hike; moderating to 7% LT as category matures
A7: Strategic Brands — net sales growth % | B7: -0.099 | C7: -0.018 | D7: 0.148 | E7: 0.15 | F7: 0.12 | G7: 0.1 | H7: 0.08 | I7: 0.08 | J7: FY25: 15% on Predator/Fury affordable EM growth; normalising to 8% by FY28+
A8: Alcohol Brands — net sales growth % | B8: N/A | C8: 0.823 | D8: -0.068 | E8: 0.05 | F8: 0.08 | G8: 0.1 | H8: 0.1 | I8: 0.1 | J8: Post-restructuring recovery; mgmt exploring intl distribution; assumes no further impairments
A9: Other (AFF third-party) — net sales growth % | B9: N/A | C9: 0.237 | D9: 0.002 | E9: 0.03 | F9: 0.03 | G9: 0.03 | H9: 0.03 | I9: 0.03 | J9: Immaterial segment; assumed ~3% p.a. growth
A11: GROSS MARGIN & OPERATING EXPENSE ASSUMPTIONS
A12: Gross margin % | B12: 0.503 | C12: 0.531 | D12: 0.54 | E12: 0.545 | F12: 0.55 | G12: 0.555 | H12: 0.558 | I12: 0.56 | J12: FY24: 54.0%; improving on pricing actions, freight tailwind & better mix; ceiling ~56% LT
A13: Distribution expense % of net sales | B13: 0.036 | C13: 0.038 | D13: 0.039 | E13: 0.039 | F13: 0.038 | G13: 0.038 | H13: 0.037 | I13: 0.037 | J13: FY24: 3.9%; stable with slight scale benefit
A14: Selling expense % of net sales | B14: 0.076 | C14: 0.084 | D14: 0.09 | E14: 0.091 | F14: 0.092 | G14: 0.09 | H14: 0.09 | I14: 0.09 | J14: FY24: 9.0%; slight rise FY26 on intl push; ~9% LT target
A15: G&A expense % of net sales (adj., ex-impair) | B15: 0.118 | C15: 0.13 | D15: 0.154 | E15: 0.135 | F15: 0.132 | G15: 0.13 | H15: 0.128 | I15: 0.125 | J15: FY24 adj ~15.4% (excl $138.8M impair); improving with scale leverage to 12.5% by FY29
A16: Non-recurring / impairment charges ($M) | B16: 138.2 | C16: 42.7 | D16: 138.8 | E16: 0 | F16: 0 | G16: 0 | H16: 0 | I16: 0 | J16: FY24 incl $138.8M Alcohol segment impairment; modeled as $0 fwd (no further assumed)
A18: D&A, CAPEX & STOCK-BASED COMPENSATION ($M)
A19: Depreciation & amortization ($M) | B19: 70.2 | C19: 84.5 | D19: 113.7 | E19: 125 | F19: 135 | G19: 145 | H19: 155 | I19: 165 | J19: Increasing with CapEx investment; ~2-yr lag between CapEx spend and D&A recognition
A20: Capital expenditures ($M) | B20: 127 | C20: 221.3 | D20: 264.1 | E20: 280 | F20: 295 | G20: 310 | H20: 320 | I20: 330 | J20: FY24: $264M; Norwalk & Athy capacity + Phoenix; CapEx/sales declines from 3.5% to ~4.3%
A21: Stock-based compensation ($M) | B21: 61.8 | C21: 68.2 | D21: 82.3 | E21: 90 | F21: 95 | G21: 100 | H21: 105 | I21: 110 | J21: FY24: $82.3M; moderate growth as company expands headcount and grants
A23: BELOW-THE-LINE ASSUMPTIONS
A24: Interest income ($M) | B24: 7.2 | C24: 130 | D24: 115 | E24: 75 | F24: 80 | G24: 85 | H24: 90 | I24: 95 | J24: FY24: $115M; declining as cash used for buybacks & CapEx; rates assumed ~4.5% on avg cash
A25: Interest expense ($M) | B25: 1.3 | C25: 0.4 | D25: 27.9 | E25: 28 | F25: 26 | G25: 24 | H25: 22 | I25: 20 | J25: FY24: $27.9M on $750M term loan; declining as debt is repaid ~$50M/yr
A26: FX & other income/(expense) ($M) | B26: -19.8 | C26: -129.9 | D26: -27.9 | E26: -15 | F26: -10 | G26: -10 | H26: -10 | I26: -10 | J26: FY24: ($26.4M) FX loss + ($1.6M) other; assumed modest FX headwind of ($15M) in FY25
A27: Effective tax rate % | B27: 0.242 | C27: 0.211 | D27: 0.241 | E27: 0.24 | F27: 0.24 | G27: 0.24 | H27: 0.24 | I27: 0.24 | J27: FY24: 24.1%; normalized at ~24% (US federal 21% + state/foreign blend)
A29: WORKING CAPITAL ASSUMPTIONS (DAYS)
A30: Days Sales Outstanding (DSO) | B30: 61.7 | C30: 61 | D30: 59.5 | E30: 58 | F30: 57 | G30: 57 | H30: 56 | I30: 56 | J30: FY24: 59.5 days (AR/Net Sales×365); gradual improvement in collections
A31: Days Inventory Outstanding (DIO) | B31: 97.2 | C31: 106 | D31: 78.1 | E31: 82 | F31: 78 | G31: 75 | H31: 73 | I31: 72 | J31: FY24: 78.1 days (post-destocking from 106 in FY23); normalising to ~72 days
A32: Days Payable Outstanding (DPO) | B32: 54.7 | C32: 61.5 | D32: 49.5 | E32: 52 | F32: 52 | G32: 52 | H32: 52 | I32: 52 | J32: FY24: 49.5 days; slight improvement in payables management to ~52 days
A34: CAPITAL STRUCTURE & BUYBACK ASSUMPTIONS
A35: Share repurchases ($M) | B35: 193 | C35: 573.8 | D35: 762.1 | E35: 500 | F35: 600 | G35: 700 | H35: 700 | I35: 700 | J35: FY24: $762M (open market) + $3B tender; assume $500-700M p.a. ongoing; ~Aug-24 plan has $500M remaining
A36: Diluted shares outstanding (M, period avg) | B36: 1066.1 | C36: 1058 | D36: 1013.1 | E36: 985 | F36: 963 | G36: 940 | H36: 916 | I36: 893 | J36: FY24: 1,013M diluted avg; declining ~2-3% p.a. via buybacks net of option exercises
A37: Long-term debt outstanding ($M, period end) | B37: 0 | C37: 0 | D37: 374 | E37: 374 | F37: 324 | G37: 274 | H37: 224 | I37: 174 | J37: FY24: $374M term loan; assumed $50M p.a. repayment; minimal additional debt
A39: VALUATION & DCF INPUTS
A40: WACC % | B40: — | C40: — | D40: 0.09 | E40: — | F40: — | G40: — | H40: — | I40: — | J40: Risk-free rate 4.3% (10yr UST) + beta 0.7 × ERP 6.5% = equity; minimal debt WACC
A41: Terminal growth rate % | B41: — | C41: — | D41: 0.04 | E41: — | F41: — | G41: — | H41: — | I41: — | J41: ~4% reflects long-term nominal energy drink category growth + international expansion
A42: EV/EBITDA exit multiple (FY2029E) | B42: — | C42: — | D42: 27 | E42: — | F42: — | G42: — | H42: — | I42: — | J42: Based on current MNST NTM EV/EBITDA ~25x; 27x reflects continued premium for growth
A43: P/E exit multiple (FY2029E) | B43: — | C43: — | D43: 30 | E43: — | F43: — | G43: — | H43: — | I43: — | J43: Current P/E ~35x; 30x reflects some multiple de-rating as growth moderates
A44: Current share price ($) | B44: — | C44: — | D44: 55 | E44: — | F44: — | G44: — | H44: — | I44: — | J44: Reference price for upside/downside calculation (update as needed)
A45: Net debt FY2024 actual ($M) | B45: — | C45: — | D45: -1159.3 | E45: — | F45: — | G45: — | H45: — | I45: — | J45: Debt $374M minus Cash $1,533M = Net Cash of $1,159M (negative net debt = net cash)
A47: Source: MNST 10-K FY2024 (Dec 31, 2024), SEC EDGAR Accession #0001410578-25-000248 | Q4 2024 Earnings Press Release (Feb 27, 2025)

Sheet Income Statement
A1: MONSTER BEVERAGE CORPORATION — CONSOLIDATED INCOME STATEMENT
A2: Historical: Blue (hardcoded from 10-K) | Forecast: Black formulas driven by Assumptions sheet | $thousands unless noted
B4: FY2022 | C4: FY2023 | D4: FY2024 | E4: FY2025E | F4: FY2026E | G4: FY2027E | H4: FY2028E | I4: FY2029E
A5: NET SALES BY SEGMENT ($THOUSANDS)
A6: Monster Energy® Drinks | B6: 5804000 | C6: 6550612 | D6: 6860146
A7: Strategic Brands | B7: 383000 | C7: 376558 | D7: 432201
A8: Alcohol Brands | B8: 101405 | C8: 184855 | D8: 172313
A9: Other | B9: 22645 | C9: 28002 | D9: 28049
A10: TOTAL NET SALES | B10: =SUM(B6:B9) -> 6311050 | C10: =SUM(C6:C9) -> 7140027 | D10: =SUM(D6:D9) -> 7492709
A11: YoY Growth % | C11: =(C10-B10)/B10 -> 0.13135326 | D11: =(D10-C10)/C10 -> 0.049395051
A13: COST OF SALES & GROSS PROFIT
A14: Cost of sales | B14: 3136483 | C14: 3345821 | D14: 3443831
A15: GROSS PROFIT | B15: =B10-B14 -> 3174567 | C15: =C10-C14 -> 3794206 | D15: =D10-D14 -> 4048878
A16: Gross margin % | B16: =B15/B10 -> 0.50301725 | C16: =C15/C10 -> 0.53139939 | D16: =D15/D10 -> 0.54037572
A18: OPERATING EXPENSES
A19: Distribution expenses | B19: 226491 | C19: 271118 | D19: 289618
A20: Selling expenses | B20: 479046 | C20: 596516 | D20: 677038
A21: General & administrative (adj.) | B21: 745801 | C21: 930000 | D21: 1013166
A22: Non-recurring / impairment charges | B22: 138198 | C22: 42736 | D22: 138762
A23: TOTAL OPERATING EXPENSES | B23: =B19+B20+B21+B22 -> 1589536 | C23: =C19+C20+C21+C22 -> 1840370 | D23: =D19+D20+D21+D22 -> 2118584
A24: Total opex % of net sales (adj. excl impairment) | B24: =(B19+B20+B21)/B10 -> 0.22996775 | C24: =(C19+C20+C21)/C10 -> 0.25176852 | D24: =(D19+D20+D21)/D10 -> 0.26423314
A26: OPERATING INCOME (EBIT) | B26: =B15-B23 -> 1585031 | C26: =C15-C23 -> 1953836 | D26: =D15-D23 -> 1930294
A27: EBIT margin % | B27: =B26/B10 -> 0.25115171 | C27: =C26/C10 -> 0.27364546 | D27: =D26/D10 -> 0.25762298
A28: Add: Depreciation & amortization ($K) | B28: 70186 | C28: 84507 | D28: 113721
A29: EBITDA | B29: =B26+B28 -> 1655217 | C29: =C26+C28 -> 2038343 | D29: =D26+D28 -> 2044015
A30: EBITDA margin % | B30: =B29/B10 -> 0.26227284 | C30: =C29/C10 -> 0.28548113 | D30: =D29/D10 -> 0.27280053
A32: NON-OPERATING INCOME / (EXPENSE)
A33: Interest income | B33: 7226 | C33: 130014 | D33: 115022
A34: Interest expense | B34: -1289 | C34: -383 | D34: -27916
A35: FX & other income/(expense) | B35: -19762 | C35: -129887 | D35: -27941
A36: Total other income/(expense), net | B36: =B33+B34+B35 -> -13825 | C36: =C33+C34+C35 -> -256 | D36: =D33+D34+D35 -> 59165
A38: INCOME BEFORE PROVISION FOR INCOME TAXES | B38: =B26+B36 -> 1571206 | C38: =C26+C36 -> 1953580 | D38: =D26+D36 -> 1989459
A39: Provision for income taxes | B39: 380340 | C39: 437494 | D39: 480411
A40: Effective tax rate % | B40: =IF(B38>0,B39/B38,0) -> 0.24206883 | C40: =IF(C38>0,C39/C38,0) -> 0.22394476 | D40: =IF(D38>0,D39/D38,0) -> 0.24147821
A42: NET INCOME | B42: =B38-B39 -> 1190866 | C42: =C38-C39 -> 1516086 | D42: =D38-D39 -> 1509048
A43: Net income margin % | B43: =B42/B10 -> 0.18869538 | C43: =C42/C10 -> 0.21233617 | D43: =D42/D10 -> 0.20140219
A45: Diluted shares outstanding (millions) | B45: 1066.1 | C45: 1058 | D45: 1013.1
A46: DILUTED EPS ($) | B46: =B42/B45/1000 -> 1.1170303 | C46: =C42/C45/1000 -> 1.4329735 | D46: =D42/D45/1000 -> 1.4895351
A47: YoY EPS growth % | C47: =IF(B46<>0,(C46-B46)/B46,"") -> 0.28284214 | D47: =IF(C46<>0,(D46-C46)/C46,"") -> 0.039471458
A49: Source: MNST 10-K FY2024, SEC EDGAR #0001410578-25-000248 | Forecast driven by Assumptions sheet

Sheet Balance Sheet
A1: MONSTER BEVERAGE CORPORATION — CONSOLIDATED BALANCE SHEET
A2: Historical: Blue (hardcoded from 10-K) | Forecast: formulas driven by IS + Assumptions | $thousands
B4: FY2022 | C4: FY2023 | D4: FY2024 | E4: FY2025E | F4: FY2026E | G4: FY2027E | H4: FY2028E | I4: FY2029E
A5: CURRENT ASSETS
A6: Cash and cash equivalents | B6: 1460000 | C6: 2297675 | D6: 1533287
A7: Short-term investments | B7: 516000 | C7: 955605 | D7: 0
A8: Accounts receivable, net | B8: 1067000 | C8: 1193964 | D8: 1221646
A9: Inventories | B9: 835000 | C9: 971406 | D9: 737107
A10: Prepaid expenses & other current assets | B10: 207000 | C10: 170346 | D10: 149464
A11: TOTAL CURRENT ASSETS | B11: =B6+B7+B8+B9+B10 -> 4085000 | C11: =C6+C7+C8+C9+C10 -> 5588996 | D11: =D6+D7+D8+D9+D10 -> 3641504
A13: NON-CURRENT ASSETS
A14: Property and equipment, net | B14: 500000 | C14: 890796 | D14: 1047024
A15: Goodwill | B15: 1375000 | C15: 1417941 | D15: 1331643
A16: Other intangible assets, net | B16: 310000 | C16: 1427139 | D16: 1414252
A17: Deferred income taxes & other non-current | B17: 320000 | C17: 285219 | D17: 284666
A18: TOTAL ASSETS | B18: =B11+B14+B15+B16+B17 -> 6590000 | C18: =C11+C14+C15+C16+C17 -> 9610091 | D18: =D11+D14+D15+D16+D17 -> 7719089
A20: CURRENT LIABILITIES
A21: Accounts payable | B21: 470000 | C21: 564379 | D21: 466775
A22: Accrued liabilities & other current | B22: 620000 | C22: 591290 | D22: 624934
A23: TOTAL CURRENT LIABILITIES | B23: =B21+B22 -> 1090000 | C23: =C21+C22 -> 1155669 | D23: =D21+D22 -> 1091709
A25: NON-CURRENT LIABILITIES
A26: Long-term debt | B26: 0 | C26: 0 | D26: 373951
A27: Deferred revenue & other LT liabilities | B27: 380000 | C27: 296089 | D27: 224817
A28: TOTAL LIABILITIES | B28: =B23+B26+B27 -> 1470000 | C28: =C23+C26+C27 -> 1451758 | D28: =D23+D26+D27 -> 1690477
A30: STOCKHOLDERS' EQUITY
A31: Common stock & additional paid-in capital | B31: 4700000 | C31: 4980728 | D31: 5150554
A32: Retained earnings | B32: 4308000 | C32: 5939736 | D32: 7448784
A33: AOCI & treasury stock, net | B33: -2516000 | C33: -2691720 | D33: -6641620
A34: TOTAL STOCKHOLDERS' EQUITY | B34: =B31+B32+B33 -> 6492000 | C34: =C31+C32+C33 -> 8228744 | D34: =D31+D32+D33 -> 5957718
A35: TOTAL LIABILITIES & EQUITY | B35: =B28+B34 -> 7962000 | C35: =C28+C34 -> 9680502 | D35: =D28+D34 -> 7648195
A37: BALANCE CHECK (TA - TL&E, should be 0) | B37: =B18-B35 -> -1372000 | C37: =C18-C35 -> -70411 | D37: =D18-D35 -> 70894 | E37: =E18-E35 -> 0 | F37: =F18-F35 -> 0 | G37: =G18-G35 -> 0 | H37: =H18-H35 -> 0 | I37: =I18-I35 -> 0

Sheet Cash Flow
A1: MONSTER BEVERAGE CORPORATION — CONSOLIDATED CASH FLOW STATEMENT
A2: Historical: Blue (hardcoded from 10-K) | Forecast: formulas | $thousands
B4: FY2022 | C4: FY2023 | D4: FY2024 | E4: FY2025E | F4: FY2026E | G4: FY2027E | H4: FY2028E | I4: FY2029E
A5: OPERATING ACTIVITIES
A6: Net income | B6: 1191624 | C6: 1630988 | D6: 1509048
A7: Add: Depreciation & amortization | B7: 70186 | C7: 84507 | D7: 113721
A8: Add: Stock-based compensation | B8: 61842 | C8: 68218 | D8: 82278
A9: Add: Impairment & non-cash charges | B9: 0 | C9: 42736 | D9: 138762
A10: Change in accounts receivable | B10: -166201 | C10: -126700 | D10: -28012
A11: Change in inventories | B11: -189234 | C11: 64600 | D11: 234299
A12: Change in accounts payable | B12: 94736 | C12: 57847 | D12: -97604
A13: Change in other working capital | B13: 105966 | C13: 96904 | D13: 3608
A14: NET CASH PROVIDED BY OPERATING ACTIVITIES | B14: 1169319 | C14: 1719100 | D14: 1927100
A16: INVESTING ACTIVITIES
A17: Capital expenditures | B17: -127049 | C17: -221312 | D17: -264118
A18: Net investments (purchase)/maturity | B18: -465000 | C18: 167700 | D18: 1032036
A19: NET CASH FROM INVESTING | B19: -592049 | C19: -53612 | D19: 764818
A21: FINANCING ACTIVITIES
A22: Share repurchases | B22: -193000 | C22: -573800 | D22: -3762100
A23: Proceeds from option exercises / ESPP | B23: 171584 | C23: 205671 | D23: 100328
A24: Net debt issuance (repayment) | B24: 0 | C24: 0 | D24: 744600
A25: NET CASH FROM FINANCING | B25: -160378 | C25: -583529 | D25: -2942890
A27: Effect of exchange rates on cash | B27: -24131 | C27: -15831 | D27: -17741
A28: NET CHANGE IN CASH & EQUIVALENTS | B28: 84258 | C28: 341538 | D28: -268713
A29: Cash, beginning of period | B29: 1376204 | C29: 1460462 | D29: 1802000
A30: Cash, end of period | B30: 1460462 | C30: 1802000 | D30: 1533287
A31: FREE CASH FLOW METRICS
A32: Free Cash Flow (OCF - CapEx) $K | B32: 1042270 | C32: 1497788 | D32: 1662982
A33: FCF margin % | B33: =B32/'Income Statement'!B10 -> 0.16515001 | C33: =C32/'Income Statement'!C10 -> 0.20977344 | D33: =D32/'Income Statement'!D10 -> 0.2219467
A34: FCF per diluted share ($) | B34: =B32/'Income Statement'!B45/1000 -> 0.9776475 | C34: =C32/'Income Statement'!C45/1000 -> 1.4156786 | D34: =D32/'Income Statement'!D45/1000 -> 1.6414786

Sheet DCF Valuation
A1: MONSTER BEVERAGE CORPORATION — DCF VALUATION & SENSITIVITY ANALYSIS
A2: Intrinsic value estimate based on 5-year FCFF DCF + exit multiple cross-check | $thousands unless noted
B3: FY2025E | C3: FY2026E | D3: FY2027E | E3: FY2028E | F3: FY2029E | G3: Total / Notes
A4: WACC (from Assumptions sheet) | G4: Change WACC in Assumptions sheet
A5: Terminal growth rate (from Assumptions sheet)
A7: STEP 1: UNLEVERED FREE CASH FLOW TO FIRM (FCFF)
A8: EBIT (from Income Statement)
A9: NOPAT = EBIT × (1 − Tax Rate)
A10: Add: D&A
A11: Less: CapEx (negative)
A12: Less: Δ Net Working Capital (negative = cash use)
A13: FREE CASH FLOW TO FIRM (FCFF)
A14: Year #
A15: Discount factor @ WACC
A16: PV of FCFF
A18: STEP 2: ENTERPRISE & EQUITY VALUE
... A21: PV of Terminal Value
A22: ENTERPRISE VALUE ($K) | G22: TV as % of EV shown below
A23: Less: Net Debt (Debt − Cash, FY2024A) [neg = net cash position]
A24: EQUITY VALUE ($K)
A25: Diluted shares outstanding FY2025E (millions)
A26: ◆ INTRINSIC VALUE PER SHARE ($)
A27: Current market price ($)
A28: Implied upside / (downside) vs. current price
A30: STEP 3A: EV/EBITDA EXIT MULTIPLE CROSS-CHECK (FY2029E)
A31: FY2029E EBITDA ($K)
A32: EV/EBITDA exit multiple
A33: Implied Enterprise Value ($K)
A34: Less: Net Debt (same FY2024A)
A35: Implied Equity Value ($K)
... A44: VALUATION SUMMARY
A45: Method | B45: Implied Price ($) | C45: Upside / (Downside)
A46: DCF (WACC / Terminal Growth) | B46: =B26 -> 0 | C46: =(B26-B27)/B27 -> #DIV/0!
A47: DCF SENSITIVITY ANALYSIS: IMPLIED PRICE PER SHARE ($) VS WACC × TERMINAL GROWTH RATE
A48: WACC ↓ / TGR → | B48: 3.0% | C48: 3.5% | D48: 4.0% | E48: 4.5% | F48: 5.0%
A49: 7.5% | B49: =(B13/(1+0.075)^1 + C13/(1+0.075)^2 + D13/(1+0.075)^3 + E13/(1+0.075)^4 + F13/(1+0.075)^5+(F13*(1+0.03)/(0.075-0.03))/(1+0.075)^5-B23)/(B25*1000) -> #DIV/0! | C49: =(B13/(1+0.075)^1 + C13/(1+0.075)^2 + D13/(1+0.075)^3 + E13/(1+0.075)^4 + F13/(1+0.075)^5+(F13*(1+0.035)/(0.075-0.035))/(1+0.075)^5-B23)/(B25*1000) -> #DIV/0! | D49: =(B13/(1+0.075)^1 + C13/(1+0.075)^2 + D13/(1+0.075)^3 + E13/(1+0.075)^4 + F13/(1+0.075)^5+(F13*(1+0.04)/(0.075-0.04))/(1+0.075)^5-B23)/(B25*1000) -> #DIV/0! | E49: =(B13/(1+0.075)^1 + C13/(1+0.075)^2 + D13/(1+0.075)^3 + E13/(1+0.075)^4 + F13/(1+0.075)^5+(F13*(1+0.045)/(0.075-0.045))/(1+0.075)^5-B23)/(B25*1000) -> #DIV/0! | F49: =(B13/(1+0.075)^1 + C13/(1+0.075)^2 + D13/(1+0.075)^3 + E13/(1+0.075)^4 + F13/(1+0.075)^5+(F13*(1+0.05)/(0.075-0.05))/(1+0.075)^5-B23)/(B25*1000) -> #DIV/0!
A50: 8.0% | B50: =(B13/(1+0.08)^1 + C13/(1+0.08)^2 + D13/(1+0.08)^3 + E13/(1+0.08)^4 + F13/(1+0.08)^5+(F13*(1+0.03)/(0.08-0.03))/(1+0.08)^5-B23)/(B25*1000) -> #DIV/0! | C50: =(B13/(1+0.08)^1 + C13/(1+0.08)^2 + D13/(1+0.08)^3 + E13/(1+0.08)^4 + F13/(1+0.08)^5+(F13*(1+0.035)/(0.08-0.035))/(1+0.08)^5-B23)/(B25*1000) -> #DIV/0! | D50: =(B13/(1+0.08)^1 + C13/(1+0.08)^2 + D13/(1+0.08)^3 + E13/(1+0.08)^4 + F13/(1+0.08)^5+(F13*(1+0.04)/(0.08-0.04))/(1+0.08)^5-B23)/(B25*1000) -> #DIV/0! | E50: =(B13/(1+0.08)^1 + C13/(1+0.08)^2 + D13/(1+0.08)^3 + E13/(1+0.08)^4 + F13/(1+0.08)^5+(F13*(1+0.045)/(0.08-0.045))/(1+0.08)^5-B23)/(B25*1000) -> #DIV/0! | F50: =(B13/(1+0.08)^1 + C13/(1+0.08)^2 + D13/(1+0.08)^3 + E13/(1+0.08)^4 + F13/(1+0.08)^5+(F13*(1+0.05)/(0.08-0.05))/(1+0.08)^5-B23)/(B25*1000) -> #DIV/0!
A51: 8.5% | B51: =(B13/(1+0.085)^1 + C13/(1+0.085)^2 + D13/(1+0.085)^3 + E13/(1+0.085)^4 + F13/(1+0.085)^5+(F13*(1+0.03)/(0.085-0.03))/(1+0.085)^5-B23)/(B25*1000) -> #DIV/0! | C51: =(B13/(1+0.085)^1 + C13/(1+0.085)^2 + D13/(1+0.085)^3 + E13/(1+0.085)^4 + F13/(1+0.085)^5+(F13*(1+0.035)/(0.085-0.035))/(1+0.085)^5-B23)/(B25*1000) -> #DIV/0! | D51: =(B13/(1+0.085)^1 + C13/(1+0.085)^2 + D13/(1+0.085)^3 + E13/(1+0.085)^4 + F13/(1+0.085)^5+(F13*(1+0.04)/(0.085-0.04))/(1+0.085)^5-B23)/(B25*1000) -> #DIV/0! | E51: =(B13/(1+0.085)^1 + C13/(1+0.085)^2 + D13/(1+0.085)^3 + E13/(1+0.085)^4 + F13/(1+0.085)^5+(F13*(1+0.045)/(0.085-0.045))/(1+0.085)^5-B23)/(B25*1000) -> #DIV/0! | F51: =(B13/(1+0.085)^1 + C13/(1+0.085)^2 + D13/(1+0.085)^3 + E13/(1+0.085)^4 + F13/(1+0.085)^5+(F13*(1+0.05)/(0.085-0.05))/(1+0.085)^5-B23)/(B25*1000) -> #DIV/0!
A52: 9.0% | B52: =(B13/(1+0.09)^1 + C13/(1+0.09)^2 + D13/(1+0.09)^3 + E13/(1+0.09)^4 + F13/(1+0.09)^5+(F13*(1+0.03)/(0.09-0.03))/(1+0.09)^5-B23)/(B25*1000) -> #DIV/0! | C52: =(B13/(1+0.09)^1 + C13/(1+0.09)^2 + D13/(1+0.09)^3 + E13/(1+0.09)^4 + F13/(1+0.09)^5+(F13*(1+0.035)/(0.09-0.035))/(1+0.09)^5-B23)/(B25*1000) -> #DIV/0! | D52: =(B13/(1+0.09)^1 + C13/(1+0.09)^2 + D13/(1+0.09)^3 + E13/(1+0.09)^4 + F13/(1+0.09)^5+(F13*(1+0.04)/(0.09-0.04))/(1+0.09)^5-B23)/(B25*1000) -> #DIV/0! | E52: =(B13/(1+0.09)^1 + C13/(1+0.09)^2 + D13/(1+0.09)^3 + E13/(1+0.09)^4 + F13/(1+0.09)^5+(F13*(1+0.045)/(0.09-0.045))/(1+0.09)^5-B23)/(B25*1000) -> #DIV/0! | F52: =(B13/(1+0.09)^1 + C13/(1+0.09)^2 + D13/(1+0.09)^3 + E13/(1+0.09)^4 + F13/(1+0.09)^5+(F13*(1+0.05)/(0.09-0.05))/(1+0.09)^5-B23)/(B25*1000) -> #DIV/0!
A53: 9.5% | B53: =(B13/(1+0.095)^1 + C13/(1+0.095)^2 + D13/(1+0.095)^3 + E13/(1+0.095)^4 + F13/(1+0.095)^5+(F13*(1+0.03)/(0.095-0.03))/(1+0.095)^5-B23)/(B25*1000) -> #DIV/0! | C53: =(B13/(1+0.095)^1 + C13/(1+0.095)^2 + D13/(1+0.095)^3 + E13/(1+0.095)^4 + F13/(1+0.095)^5+(F13*(1+0.035)/(0.095-0.035))/(1+0.095)^5-B23)/(B25*1000) -> #DIV/0! | D53: =(B13/(1+0.095)^1 + C13/(1+0.095)^2 + D13/(1+0.095)^3 + E13/(1+0.095)^4 + F13/(1+0.095)^5+(F13*(1+0.04)/(0.095-0.04))/(1+0.095)^5-B23)/(B25*1000) -> #DIV/0! | E53: =(B13/(1+0.095)^1 + C13/(1+0.095)^2 + D13/(1+0.095)^3 + E13/(1+0.095)^4 + F13/(1+0.095)^5+(F13*(1+0.045)/(0.095-0.045))/(1+0.095)^5-B23)/(B25*1000) -> #DIV/0! | F53: =(B13/(1+0.095)^1 + C13/(1+0.095)^2 + D13/(1+0.095)^3 + E13/(1+0.095)^4 + F13/(1+0.095)^5+(F13*(1+0.05)/(0.095-0.05))/(1+0.095)^5-B23)/(B25*1000) -> #DIV/0!
